{
  "culturalFestivals" : [ {
    "name" : "Lễ hội Đống Đa",
    "date" : "5/1",
    "location" : "Hà Nội, quận Đống Đa",
    "historicalFiguresList" : [ "Nguyễn Huệ" ]
  }, {
    "name" : "Hội vật Liễu Đôi",
    "date" : "5/1",
    "location" : "Hà Nam, huyện Thanh Liêm",
    "historicalFiguresList" : [ "" ]
  }, {
    "name" : "hội Gióng Sóc Sơn",
    "date" : "6/1",
    "location" : "Hà Nội, Sóc Sơn",
    "historicalFiguresList" : [ "Thánh Gióng" ]
  }, {
    "name" : "Lễ hội Cổ Loa",
    "date" : "6/1",
    "location" : "Hà Nội, Đông Anh",
    "historicalFiguresList" : [ "An Dương Vương" ]
  }, {
    "name" : "Lễ hội chùa Bái Đính",
    "date" : "6/1",
    "location" : "Ninh Bình, Gia Viễn",
    "historicalFiguresList" : [ "" ]
  }, {
    "name" : "Chợ Viềng",
    "date" : "7/1",
    "location" : "Nam Định, Vụ Bản",
    "historicalFiguresList" : [ "" ]
  }, {
    "name" : "Lễ hội đầm Ô Loan",
    "date" : "7/1",
    "location" : "Phú Yên, Ô Loan",
    "historicalFiguresList" : [ "" ]
  }, {
    "name" : "Đại lễ Đức Chí Tôn",
    "date" : "9/1",
    "location" : "Tây Ninh, Đạo Cao Đài",
    "historicalFiguresList" : [ "Đức Chí Tôn" ]
  }, {
    "name" : "Hội xuân Yên Tử",
    "date" : "10/1",
    "location" : "Quảng Ninh, núi Yên Tử",
    "historicalFiguresList" : [ "Trần Nhân Tông" ]
  }, {
    "name" : "Hội phết Hiền Quan",
    "date" : "13/1",
    "location" : "Phú Thọ, huyện Tam Nông",
    "historicalFiguresList" : [ "Thiều Hoa công chúa", " Mộc trang đại vương" ]
  }, {
    "name" : "Hội Lim",
    "date" : "13/1",
    "location" : "Bắc Ninh, huyện Tiên Du",
    "historicalFiguresList" : [ "Nguyễn Đình Diễn" ]
  }, {
    "name" : "Lễ hội chùa Hương",
    "date" : "6/1",
    "location" : "Hà Nội, huyện Mỹ Đức",
    "historicalFiguresList" : [ "Quan Thế Âm Bồ Tát" ]
  }, {
    "name" : "Hội chùa Côn Sơn",
    "date" : "15/1",
    "location" : "Hải Dương, huyện Chí Linh",
    "historicalFiguresList" : [ "Huyền Quang", " Nguyễn Trãi" ]
  }, {
    "name" : "Lễ hội làm chay",
    "date" : "14/1",
    "location" : "Long An, thị trấn Tầm Vu",
    "historicalFiguresList" : [ "Đỗ Tường Phong", " Đỗ Tường Tự" ]
  }, {
    "name" : "Tết Nguyên tiêu",
    "date" : "15/1",
    "location" : "Nhiều quốc gia",
    "historicalFiguresList" : [ "" ]
  }, {
    "name" : "Lễ hội chọi trâu",
    "date" : "16/1",
    "location" : "Vĩnh Phúc, huyện Lập Thạch",
    "historicalFiguresList" : [ "" ]
  }, {
    "name" : "Hội Xuân núi Bà",
    "date" : "4/1",
    "location" : "Tây Ninh, Núi Bà Đen",
    "historicalFiguresList" : [ "Linh Sơn Thánh Mẫu" ]
  }, {
    "name" : "Lễ hội đình Yên Phụ",
    "date" : "10/2",
    "location" : "Hà Nội, Hồ Tây",
    "historicalFiguresList" : [ "Uy Linh Lang", " Vương Duy", " Vương Ba" ]
  }, {
    "name" : "Lễ hội Miếu Mạch Lũng",
    "date" : "10/2",
    "location" : "Hà Nội, Đông Anh",
    "historicalFiguresList" : [ "Minh Mỗ Đại vương Thượng đẳng thần" ]
  }, {
    "name" : "Lễ hội Quán Thế Âm",
    "date" : "19/2",
    "location" : "Đà Nẵng, Ngũ Hành Sơn",
    "historicalFiguresList" : [ "Quán Thế Âm Bồ Tát" ]
  }, {
    "name" : "Tiết Thanh minh",
    "date" : "",
    "location" : "",
    "historicalFiguresList" : [ "" ]
  }, {
    "name" : "Hội đua voi",
    "date" : "",
    "location" : "Tây Nguyên",
    "historicalFiguresList" : [ "" ]
  }, {
    "name" : "Tết Hàn thực",
    "date" : "3/3",
    "location" : "",
    "historicalFiguresList" : [ "Giới Tử Thôi", " Tấn Văn Công" ]
  }, {
    "name" : "Hội Phủ Giầy",
    "date" : "3/3",
    "location" : "Nam Định, Vụ Bản",
    "historicalFiguresList" : [ "Mẫu Liễu Hạnh" ]
  }, {
    "name" : "Lễ hội Điện Hòn Chén",
    "date" : "2/3",
    "location" : "Thừa Thiên Huế, huyện Hương Trà",
    "historicalFiguresList" : [ "Thiên Y A Na" ]
  }, {
    "name" : "Lễ hội Chùa Thầy",
    "date" : "3/3",
    "location" : "Hà Tây, Quốc Oai",
    "historicalFiguresList" : [ "Từ Đạo Hạnh" ]
  }, {
    "name" : "Lễ hội Hoa Lư",
    "date" : "6/3",
    "location" : "Ninh Bình, huyện Hoa Lư",
    "historicalFiguresList" : [ "Đinh Bộ Lĩnh" ]
  }, {
    "name" : "Lễ hội đền Thái Vi",
    "date" : "14/3",
    "location" : "Ninh Bình, huyện Hoa Lư",
    "historicalFiguresList" : [ "Trần Thái Tông", " Trần Thánh Tông", " Trần Nhân Tông", " Trần Anh Tông", " Hiển Từ Hoàng Thái Hậu" ]
  }, {
    "name" : "Lễ hội Nam Trì",
    "date" : "8/3",
    "location" : "Hưng Yên, huyện Ân Thi",
    "historicalFiguresList" : [ "Lang Công", " Bảo Công", " Công chúa Hùng vương Lâu nương" ]
  }, {
    "name" : "Giỗ tổ Hùng Vương",
    "date" : "10/3",
    "location" : "Nhiều nơi ở Việt Nam",
    "historicalFiguresList" : [ "Vua Hùng" ]
  }, {
    "name" : "Lễ hội đền Mẫu",
    "date" : "10/3",
    "location" : "Hưng Yên, Phố Hiến",
    "historicalFiguresList" : [ "Dương Quý Phi" ]
  }, {
    "name" : "Lễ hội Làng cá Cát Bà",
    "date" : "",
    "location" : "Hải Phòng, huyện Cát Hải, Thị trấn Cát Bà",
    "historicalFiguresList" : [ "Hồ Chí Minh" ]
  }, {
    "name" : "Hội Gióng Phù Đổng",
    "date" : "7/4",
    "location" : "Hà Nội, huyện Gia Lâm",
    "historicalFiguresList" : [ "Thánh Gióng" ]
  }, {
    "name" : "Lễ Phật Đản",
    "date" : "8/4",
    "location" : "Nhiều quốc gia",
    "historicalFiguresList" : [ "Phật Tất Đạt Đa" ]
  }, {
    "name" : "Lễ hội Chol Chnam Thmay",
    "date" : "14/4",
    "location" : "Nam Bộ",
    "historicalFiguresList" : [ "" ]
  }, {
    "name" : "Lễ khao lề thế lính",
    "date" : "18/3",
    "location" : "Quảng Ngãi, huyện Lý Sơn",
    "historicalFiguresList" : [ "" ]
  }, {
    "name" : "Lễ hội miếu Bà Chúa Xứ",
    "date" : "23/4",
    "location" : "Miếu Bà Chúa Xứ, Núi Sam, An Giang, Châu Đốc",
    "historicalFiguresList" : [ "Bà Chúa Xứ" ]
  }, {
    "name" : "Tết Đoan ngọ",
    "date" : "5/5",
    "location" : "Nhiều quốc gia",
    "historicalFiguresList" : [ "" ]
  }, {
    "name" : "Thất Tịch",
    "date" : "7/7",
    "location" : "Nhiều quốc gia",
    "historicalFiguresList" : [ "Ngưu Lang", " Chức Nữ" ]
  }, {
    "name" : "Lễ Vu Lan, Tết Trung Nguyên",
    "date" : "15/7",
    "location" : "Nhiều quốc gia",
    "historicalFiguresList" : [ "Bồ tát Mục Liên" ]
  }, {
    "name" : "Lễ hội Nghinh Ông (Quan Thánh Đế Quân)",
    "date" : "",
    "location" : "Phan Thiết (Bình Thuận)",
    "historicalFiguresList" : [ "" ]
  }, {
    "name" : "Lễ hội Katê",
    "date" : "",
    "location" : "Bình Thuận",
    "historicalFiguresList" : [ "" ]
  }, {
    "name" : "Lễ hội chọi trâu",
    "date" : "9/8",
    "location" : "Hải Phòng, Đồ Sơn",
    "historicalFiguresList" : [ "" ]
  }, {
    "name" : "Tết Trung Thu",
    "date" : "15/8",
    "location" : "Nhiều quốc gia",
    "historicalFiguresList" : [ "Hằng Nga", " Hậu Nghệ", " Đường Minh Hoàng", " Chú Cuội" ]
  }, {
    "name" : "Hội Đền Kiếp Bạc",
    "date" : "15/8",
    "location" : "Hải Dương, huyện Chí Linh",
    "historicalFiguresList" : [ "Trần Hưng Đạo" ]
  }, {
    "name" : "Hội Yến Diêu Trì",
    "date" : "15/8",
    "location" : "Tây Ninh, Tòa Thánh Tây Ninh",
    "historicalFiguresList" : [ "Cao Quỳnh Cư", " Phạm Công Tắc", " Cao Hoài Sang", " Nguyễn Thị Hiếu" ]
  }, {
    "name" : "Lễ hội Nghinh Ông (Cá Voi)",
    "date" : "",
    "location" : "Bình Thuận, Tiền Giang",
    "historicalFiguresList" : [ "" ]
  }, {
    "name" : "Lễ hội AHDT Nguyễn Trung Trực",
    "date" : "",
    "location" : "Rạch Giá, Kiên Giang",
    "historicalFiguresList" : [ "Nguyễn Trung Trực" ]
  }, {
    "name" : "Lễ hội Chùa Keo",
    "date" : "13/9",
    "location" : "Thái Bình, Vũ Thư",
    "historicalFiguresList" : [ "Thiền sư Không Lộ" ]
  }, {
    "name" : "Tết cơm mới",
    "date" : "15/10",
    "location" : "Nhiều quốc gia",
    "historicalFiguresList" : [ "" ]
  }, {
    "name" : "Lễ hội đền Nguyễn Công Trứ",
    "date" : "13/11",
    "location" : "Ninh Bình, huyện Kim Sơn",
    "historicalFiguresList" : [ "Nguyễn Công Trứ" ]
  }, {
    "name" : "Tiễn Ông Táo về trời",
    "date" : "23/12",
    "location" : "Nhiều quốc gia",
    "historicalFiguresList" : [ "Thổ Công", " Thổ địa", " Thổ kỳ" ]
  } ]
}